finegrained/__init__.py
finegrained/cli.py
finegrained/data/__init__.py
finegrained/data/annotations.py
finegrained/data/brain.py
finegrained/data/display.py
finegrained/data/export.py
finegrained/data/tag.py
finegrained/data/transforms.py
finegrained/data/zoo.py
finegrained/models/__init__.py
finegrained/models/embed.py
finegrained/models/flash_base.py
finegrained/models/flash_transforms.py
finegrained/models/image_classification.py
finegrained/models/image_metalearn.py
finegrained/models/image_selfsupervised.py
finegrained/models/torch_utils.py
finegrained/models/transformers_base.py
finegrained/models/yolo.py
finegrained/services/__init__.py
finegrained/services/tracking.py
finegrained/storage/__init__.py
finegrained/storage/create.py
finegrained/storage/index.py
finegrained/utils/__init__.py
finegrained/utils/data.py
finegrained/utils/dataset.py
finegrained/utils/general.py
finegrained/utils/milvus.py
finegrained/utils/mlflow_server.py
finegrained/utils/os_utils.py
finegrained/utils/similarity.py
finegrained/utils/triton.py
finegrained/utils/triton_python/image_classification.py
finegrained/utils/triton_python/transformers_tokenizer.py
finegrained/utils/triton_python/triton_python_backend_utils.py
finegrained/utils/types.py
finegrained-0.1.4.dist-info/LICENSE
finegrained-0.1.4.dist-info/METADATA
finegrained-0.1.4.dist-info/WHEEL
finegrained-0.1.4.dist-info/entry_points.txt
finegrained-0.1.4.dist-info/RECORD
