Metadata-Version: 2.1
Name: finegrained
Version: 0.1.4
Summary: Quickly prepare data, train new models and export to production from a command line
License: MIT
Author: Rustem Galiullin
Author-email: rustemgal@gmail.com
Requires-Python: >=3.9,<4.0
Classifier: License :: OSI Approved :: MIT License
Classifier: Operating System :: OS Independent
Classifier: Programming Language :: Python :: 3
Classifier: Programming Language :: Python :: 3.9
Classifier: Programming Language :: Python :: 3.10
Classifier: Programming Language :: Python :: 3.11
Requires-Dist: fiftyone (>=0.21.6,<0.22.0)
Requires-Dist: fire (>=0.5.0,<0.6.0)
Requires-Dist: numpy (>=1.22.4,<2.0.0)
Requires-Dist: pillow (>=9.4.0,<10.0.0)
Requires-Dist: pyyaml (>=6.0,<7.0)
Requires-Dist: scikit-learn (>=1.2.2,<2.0.0)
Requires-Dist: tqdm (>=4.65.0,<5.0.0)
